{
  "source_file": "琳妮特.wikitext",
  "blocks": [
    {
      "type": "template",
      "name": "面包屑",
      "args": [
        "角色"
      ],
      "data": {},
      "text": "面包屑|角色"
    },
    {
      "type": "template",
      "name": "角色导航",
      "args": [],
      "data": {},
      "text": "角色导航"
    },
    {
      "type": "template",
      "name": "角色",
      "args": [],
      "data": {
        "名称": "琳妮特",
        "称号": "丽影绮行",
        "全名": "琳妮特·雪奈茨芙娜",
        "英文名称": "Lynette Snezhevna",
        "稀有度": "4星",
        "所属": "枫丹",
        "种族": "兽人（猫）",
        "介绍": "寡言少语，罕有表情的魔术助手，性情像猫一样难以猜测。",
        "元素属性": "风",
        "武器类型": "单手剑",
        "始基力": "荒性",
        "命之座": "白尾猫座",
        "特殊料理": "午后闲茶",
        "性别": "女",
        "TAG": "嘲讽、聚怪、加攻、水下探索便利、快速移动、生命损耗、自身治疗、自身附魔、自身伤害提升、元素转化",
        "限定": "否",
        "实装日期": "2023年08月16日",
        "实装版本": "4.0"
      },
      "text": "角色\n|名称=琳妮特\n|称号=丽影绮行\n|全名=琳妮特·雪奈茨芙娜\n|英文名称=Lynette Snezhevna\n|稀有度=4星\n|所属=枫丹\n|种族=兽人（猫）\n|介绍=寡言少语，罕有表情的魔术助手，性情像猫一样难以猜测。\n|元素属性=风\n|武器类型=单手剑\n|始基力=荒性\n|命之座=白尾猫座\n|特殊料理=午后闲茶\n|性别=女\n|TAG=嘲讽、聚怪、加攻、水下探索便利、快速移动、生命损耗、自身治疗、自身附魔、自身伤害提升、元素转化\n|限定=否\n|实装日期=2023年08月16日\n|实装版本=4.0"
    },
    {
      "type": "template",
      "name": "角色/属性数据",
      "args": [],
      "data": {
        "生命上限": "1039",
        "20生命上限": "2670",
        "20+生命上限": "3447",
        "40生命上限": "5163",
        "40+生命上限": "5715",
        "50生命上限": "6573",
        "50+生命上限": "7309",
        "60生命上限": "8168",
        "60+生命上限": "8719",
        "70生命上限": "9577",
        "70+生命上限": "10129",
        "80生命上限": "10987",
        "80+生命上限": "11539",
        "90生命上限": "12397",
        "攻击力": "20",
        "20攻击力": "50",
        "20+攻击力": "65",
        "40攻击力": "97",
        "40+攻击力": "107",
        "50攻击力": "123",
        "50+攻击力": "137",
        "60攻击力": "153",
        "60+攻击力": "163",
        "70攻击力": "179",
        "70+攻击力": "189",
        "80攻击力": "205",
        "80+攻击力": "216",
        "90攻击力": "232",
        "防御力": "60",
        "20防御力": "153",
        "20+防御力": "198",
        "40防御力": "296",
        "40+防御力": "328",
        "50防御力": "377",
        "50+防御力": "420",
        "60防御力": "469",
        "60+防御力": "501",
        "70防御力": "550",
        "70+防御力": "582",
        "80防御力": "631",
        "80+防御力": "663",
        "90防御力": "712",
        "突破加成属性": "风元素伤害加成",
        "突破20": "0.0%",
        "未破40": "0.0%",
        "突破40": "6.0%",
        "未破50": "6.0%",
        "突破50": "12.0%",
        "未破60": "12.0%",
        "突破60": "12.0%",
        "未破70": "12.0%",
        "突破70": "18.0%",
        "未破80": "18.0%",
        "突破80": "24.0%",
        "未破90": "24.0%",
        "突破90": "无"
      },
      "text": "角色/属性数据\n|生命上限=1039\n|20生命上限=2670\n|20+生命上限=3447\n|40生命上限=5163\n|40+生命上限=5715\n|50生命上限=6573\n|50+生命上限=7309\n|60生命上限=8168\n|60+生命上限=8719\n|70生命上限=9577\n|70+生命上限=10129\n|80生命上限=10987\n|80+生命上限=11539\n|90生命上限=12397\n|攻击力=20\n|20攻击力=50\n|20+攻击力=65\n|40攻击力=97\n|40+攻击力=107\n|50攻击力=123\n|50+攻击力=137\n|60攻击力=153\n|60+攻击力=163\n|70攻击力=179\n|70+攻击力=189\n|80攻击力=205\n|80+攻击力=216\n|90攻击力=232\n|防御力=60\n|20防御力=153\n|20+防御力=198\n|40防御力=296\n|40+防御力=328\n|50防御力=377\n|50+防御力=420\n|60防御力=469\n|60+防御力=501\n|70防御力=550\n|70+防御力=582\n|80防御力=631\n|80+防御力=663\n|90防御力=712\n\n|突破加成属性=风元素伤害加成\n|突破20=0.0%\n|未破40=0.0%\n|突破40=6.0%\n|未破50=6.0%\n|突破50=12.0%\n|未破60=12.0%\n|突破60=12.0%\n|未破70=12.0%\n|突破70=18.0%\n|未破80=18.0%\n|突破80=24.0%\n|未破90=24.0%\n|突破90=无"
    },
    {
      "type": "template",
      "name": "角色/突破简",
      "args": [],
      "data": {
        "突破特产材料": "柔灯铃",
        "突破晶石材料序列": "自在松石",
        "突破BOSS材料": "奇械发条备件·歌裴莉娅",
        "突破普通材料序列": "齿轮",
        "20级新天赋": "巧施协同",
        "60级新天赋": "道具完备"
      },
      "text": "角色/突破简\n|突破特产材料=柔灯铃\n|突破晶石材料序列=自在松石\n|突破BOSS材料=奇械发条备件·歌裴莉娅\n|突破普通材料序列=齿轮\n|20级新天赋=巧施协同\n|60级新天赋=道具完备"
    },
    {
      "type": "template",
      "name": "角色立绘",
      "args": [],
      "data": {},
      "text": "角色立绘"
    },
    {
      "type": "template",
      "name": "角色/信息",
      "args": [],
      "data": {
        "昵称/外号": "枫丹猫猫、机械杀手",
        "中文CV": "可可味",
        "日文CV": "篠原侑",
        "英文CV": "阿奈丽丝·基尼奥内斯",
        "韩文CV": "李瑟琳娜",
        "体型": "少女",
        "生日": "2月2日",
        "个人任务": "邀约事件·琳妮特",
        "衣装名称": "魅影猫",
        "归属": "布法蒂公馆",
        "职业": "「多功能魔术助理机关」",
        "名片名称": "琳妮特·成真",
        "名片描述": "魔术有一大分类就是「突然出现」。琳妮特平常虽然都在节约能量，但是认真的一面也会像是魔术帽里的鸽子一样突然出现。"
      },
      "text": "角色/信息\n|昵称/外号=枫丹猫猫、机械杀手\n|中文CV=可可味\n|日文CV=篠原侑\n|英文CV=阿奈丽丝·基尼奥内斯\n|韩文CV=李瑟琳娜\n|体型=少女\n|生日=2月2日\n|个人任务=邀约事件·琳妮特\n|衣装名称=魅影猫\n|归属=布法蒂公馆\n|职业=「多功能魔术助理机关」\n|名片名称=琳妮特·成真\n|名片描述=魔术有一大分类就是「突然出现」。琳妮特平常虽然都在节约能量，但是认真的一面也会像是魔术帽里的鸽子一样突然出现。"
    },
    {
      "type": "template",
      "name": "角色/故事",
      "args": [],
      "data": {
        "角色详细": "提起枫丹廷最有名气的魔术师，观众一定会想起舞台上神采飞扬的林尼。\n但提起枫丹廷最有名气的魔术助手，观众们就往往摸头不着，莫衷一是了。\n喝彩并非为她而起，掌声亦非为她而鸣。身为助手，她只会在必要的时机引开观众注意，再将高光时刻还予主角。\n无论是在台上还是台下，琳妮特总是习惯性地将自己藏在林尼身后，那一小块灯光与赞誉都照不进的影子里。\n对于一名魔术助手而言，保持低调是一种职业素养。\n对于「家」里的孩子而言…隐匿于影，更是一种生存之道。",
        "角色故事1": "琳妮特常把「待机」、「节能」之类的说辞挂在嘴边，借此规避不必要的麻烦。\n遇上不想干的杂务，如果说自己正在「发呆」，十有八九会招来一句「那不就是有空吗！」接着继续被强人所难。\n但如果一本正经地宣称自己正处于「待机模式」、必须「节约能量」，配合琳妮特雕塑般的表情，就足以令对方懵怔一时。\n趁着这个空当，琳妮特就可以顶着一副严肃面孔，平静从容地逃离现场了。\n这一出对付熟人并不好用，不过能与琳妮特相熟的人，大多清楚琳妮特怕麻烦的性格，更清楚…让她做杂务的后果。\n尽管嘴里常念一些机械专有名词，但琳妮特对机械知识的了解，恐怕也仅限于此。\n在琳妮特的家里流传着这样的劝诫：不要让琳妮特单独与洗碗机、吸尘器等任何一部机械同处一室。\n否则在第三方——往往是菲米尼——赶到之时，机械只会落得两种下场：\n一、机械坏得莫名其妙：洗碗机口吐白沫、吸尘器倒地抽搐…琳妮特一脸无辜地站在满地狼藉之间；\n二、机械安然无恙，杂务全无进度，琳妮特窝在角落里偷闲安睡。\n鉴于在开门前两种结果无法预测，且无论哪种都有害无益，琳妮特心安理得地告别了所有家务。\n不过说来也怪，明明不管多简单的机械都记不得操作、三两下就能弄坏…\n唯独在操纵魔术机关时，琳妮特却比林尼还要全神贯注，旷日经年，从不出错。",
        "角色故事2": "从某种角度来说，「魔术助手」是一个矛盾的职业。\n台上的喝彩与掌声，属于身为主角的魔术师；台下的鲜花与名利，也不曾眷顾主角的助手。\n然而一出精彩的表演，却又少不得助手的配合。\n身为舞台上最接近魔术师的人，助手清楚魔术师所有的隐秘，在危险的表演中，助手的一举一动更牵连着魔术师的生死。\n舞台上的魔术师与助手就如双面的镜子，一面向光，吸引观众的注意；一面朝暗，在背后完成手法，两面彼此轮转，变幻无常。\n要想配合得圆融如意，助手本人的魔术造诣，就不能比魔术师低多少。\n可有了这等技艺，又怎么会甘心久居人下？是以大多数学徒出身的助手，在学艺有成后就会自立门户，不会永远安于助手之位。\n林尼出道成名以后，也有不少名流看中了琳妮特身上的潜力，觉得她若独立出来，肯定能成为更耀眼的明星，甚至还有人想邀请她出演映影片的女主角。\n猫耳、少女、魔术师…光是这些噱头一堆，就足以赚满眼球！\n无奈琳妮特自己对这些盛情置若罔闻，不但拒绝了所有挖角…甚至连拒绝的理由也懒得编，所有回信都扔给林尼来写。\n这可愁苦了林尼，这些观众大多身份显赫，「父亲」大人吩咐过不能轻慢。\n如果被发现试图从林尼处挖角的信是由林尼本人回的，下次见面恐怕会相当尴尬。\n于是他只能模仿琳妮特的口吻，编出一封封的礼数周全，态度恳切的拒信。\n即使巧舌如林尼，要用琳妮特平日那副惜字如金的口吻写这种信，也是相当费心思的。\n每每写到心累手酸，看着一旁正悠然趴在沙发上的琳妮特，林尼也忍不住想想：要不然真让她去试试吧？换我做助手也行。\n「…别想。」琳妮特敏锐地捕捉到这一闪而过的念头，伸个懒腰翻身看向林尼，「我就喜欢当你的助手。」",
        "角色故事3": "泡茶是琳妮特为数不多的爱好之一。\n看着茶盏上氤氲的气旋，闻着淡雅的清香，一整天的疲惫都会烟消云散。\n每逢贵客上门，多是由林尼出面相谈，琳妮特以茶待客；家里办起茶话会来，也多是她来负责泡茶，其他家人负责说话。\n在旁人或高谈阔论，或清聊闲谈时，琳妮特总是坐在一边，双手捧杯，默默吹凉，小口啜饮。\n她的舌头天生敏感，喝不得太烫的茶水。\n但用温水冲茶，简直是暴殄天物；至于往茶里加冰、拿两个杯子来回倒茶降温之类的，更会被琳妮特斥为邪道。\n加冰会影响茶的浓度，倒茶会破坏口感层次…只有小口小口地吹凉，才能把握好最佳的温度，既不被烫着，又不失风味。\n等茶温降到可以入口，也不该急着饮尽。\n一些茶越是见底，风味越是浓郁，一口入喉总要先回味几分钟，才能继续品鉴。所以她喝起茶来总是慢条斯理。\n等到茶壶倒空，天也就差不多聊完了。\n至于剩下的一桌茶具…就交给别人收拾吧，免得又把洗碗机弄坏了。",
        "角色故事4": "曾有一位枫丹官员，想调查「布法蒂公馆」近几个月的资金流动。\n然而调查计划才刚拟出个草案，就被他的上司草草叫停。\n这位官员怎么也想不到，上司叫停调查是因为收到了一封信，随信还附了一组他与一位名媛幽会的画片。\n这名上司也怎么都想不到，这则秘密暴露的契机，仅仅是在一场魔术演出时，他掏出了一块不属于他夫人的手帕。\n当时他正感动于台上的精彩表演，却忽略了自暗处投来的另一道视线。\n这片刻的分神足够让琳妮特在对方毫无觉察的情况下，「偷走」他身上所有情报。\n人们会不自觉地暴露自己，服饰、眼神、肢体动作、甚至语气中的沉默…\n常人无法从中读出什么，是因为信息往往埋没于茫茫多的细节之中，而琳妮特却能以非同寻常的观察力，从中捕捉到关键。\n将无数看似琐碎的细节串联之后，就能引出对公馆有用的情报。\n一人在明，一人在暗，公馆的这对「眼睛」，已经从枫丹名流身上盗走无数隐秘。被盗者惘然不觉，宛如身处一场魔术。\n保持敏锐需要精神的绝对集中，因此工作中的琳妮特总是寡言少语，节省心力。\n即使是在日常休息，她也会习惯性地过滤掉各种无用信息。\n…只是这时候什么信息有用，什么无用，就全凭琳妮特的一己之好了。\n比如各种机械操作和家务技能，只要完全不去做家务，就可以理直气壮的置之脑后。\n又比如茶话会上的闲聊八卦，只要适当地接一句「原来如此」、「竟然是这样」、「然后呢」…就可以顺利推进对话。\n节能省力，颇合心意。",
        "角色故事5": "常有人以为，琳妮特的猫耳也是演出服的一部分。因为哥哥林尼与她流着同样的血，外表却与常人无异。\n可琳妮特多出的一对耳朵一条尾巴，却是实打实的长在身上，真得不能再真。\n据说这种类似猫的性状，往往会伴着血缘遗传，即便后代血脉日渐稀薄，偶尔也会出现「返祖现象」。\n年幼时的琳妮特，并不喜欢这份来自先祖的馈赠。\n总有好事的孩子，或有心或无意，指着它们问琳妮特：为什么你跟大家不一样？你跟林尼是不是亲生的兄妹？\n内向的琳妮特不知如何作答，林尼也不能总陪在她身边。每逢这时，她只能压着耳朵、卷起尾巴，蹲在角落里独自伤心。\n只有街头巷尾的流浪猫们会来安慰琳妮特，绕着她的脚踝轻蹭。\n不能带着这幅表情去见林尼。她心里很清楚。哥哥要操心的事已经很多了，不该再为这点幼稚的事情困扰。\n但强装无事也肯定会被他看穿，想要瞒过天才的魔术师，必须先瞒过自己。\n琳妮特抱起脚边的小猫，轻抚它背上的毛发。感受着它的呼吸，琳妮特的情绪渐渐缓和下来。\n小猫跳出了她的怀抱，她的脸上也已恢复了往日的平静。\n枫丹贵族中还有一些以追寻新奇为乐的败类。一场宴会上，一名「大人物」就相中了琳妮特的不同寻常。\n当时的养父不假思索地将她塞进了「大人物」的车里，不管她的反对，不顾她的挣扎，仿佛只是送出了一只会挠沙发的宠物猫。\n为什么是自己？为什么自己会长这对耳朵？\n令人窒息的孤独中，琳妮特终于压抑不住心中多年的积郁，痛苦地盖住了耳朵。\n「别再躲躲藏藏了，胆怯是无用的。」直到一个声音，与月光一起映入黑暗，「出来吧。想害你的人已经死了。」\n那声音冷酷而肃杀，却又有一种令人安心的魔力。琳妮特抬眼，望向日后的「父亲」。\n「不错的耳朵，可以用来监听。从今往后，学会利用它们吧。」\n「父亲」揉着琳妮特的耳朵，手法并不温柔，言辞并不温和，与那夜的月光一样清冷。\n也像月光一样，照亮一角黑暗。\n……\n「猫的耳朵向后翻折，往往是在恐惧或者警戒，向前竖起多半表示心情愉快…」\n林尼向布法蒂公馆的新成员科普猫的习性时，总会忍不住偷眼去看一旁的妹妹。\n琳妮特的耳朵正朝前竖着，偶尔向外扑闪。\n它们已经很久没再向后翻折了。",
        "冒险笔记名称": "「非自动」喂食机",
        "冒险笔记": "菲米尼帮忙订做的自动给食机关，用以应付家里越来越多的小动物。\n某场演出结束后，琳妮特在剧院后门发现了一口被遗弃的箱子。\n打开箱盖，几只不足月的幼猫惊惶地抬头，却饿得没有力气逃窜，只能紧张地盯着她的眼睛。\n琳妮特没说话，也没伸手惊扰，只是默默与它们对视。\n慢慢地，幼猫们似乎明白了琳妮特并无恶意，终于垂下了仰得酸痛的小脑袋。\n琳妮特这才抱起箱子，一箱小猫不吵不闹，安静地趴在箱底，等待面前的少女将它们带去新的「家庭」。\n关于是否收留这些小动物，家人们进行过一番小小的争论，一向寡言少语的琳妮特这时却一反常态，执意要留下它们。\n事情最后竟传到了「父亲」耳朵里，她一锤定音，要孩子们停止这番无聊的吵闹。\n「要养的自己去养就好了，记得自己管教好，别给其他人添麻烦。」\n沉默片刻，又补上一句：「如果在今年的冬天结束之前，还没教会它们怎么守规矩，就自己处理掉它们吧。」\n「父亲」如此表态，正反双方也都不好再说什么。至于教养它们的任务，则落到了琳妮特身上。\n鉴于琳妮特平日里总是一副怕麻烦的样子，菲米尼特意订做了一台自动喂食机。\n这台机器内置计时与称重机关，还有可以防潮的轮盘式粮箱，可以定时定量为小猫们提供各种食粮。\n这也成了少数在琳妮特手下幸存的机械之一，服役多年都没出过故障，内部结构更是焕然如新，只有出粮口下方的盘子有经常使用的痕迹。\n——因为琳妮特就没正经用过它。\n每个箱格里要加什么类型的食粮、如何设置供餐时间和供餐量…比起牢记这些，还是每天亲手准备猫食装进盘里比较方便。\n更何况，如果连喂食都交给机械的话…\n琳妮特蹲在「非自动」喂食机旁，一边帮吃饱喝足的猫顺毛，一边默默地想着。\n…又怎么能教好这些孩子呢？",
        "神之眼": "小时候，琳妮特常听林尼讲神之眼的故事。\n故事里的主角仿佛无所不能，勾勾手指就能卷起风暴，轻轻呵气就能吹散阴霾。\n那不是精心准备的魔术，而是货真价实的奇迹。\n如果我们也有神之眼就好了。彼时的琳妮特常想。\n能让魔术变成真正的魔法。能从帽子里变出果腹的食物、取暖的篝火。能让林尼不用总为了生计奔波。\n但神明并未垂听她的祈祷。后来的日子里，她和林尼继续流浪，在都市街头与贵族府邸间几经辗转，终于在「父亲」的庇护下寻得一隅落脚之地。\n两人深知这机会来之不易，熬过严苛的训练，彼此支撑着完成无数任务。\n现实早早地磨洗了童真，对神之眼的幻想也被遗忘在久远的过去。\n某次行动中，他们被派去一名贵族的山间别馆表演魔术，伺机盗取目标藏于书房的犯罪证据。\n任务本身再普通不过，进行得也很顺利。借演出的机会，两人在别馆的门窗上做了手脚。等到表演结束，再悄悄折返潜入，就能神不知鬼不觉地偷走罪证。\n然而就在他们得手之际，窗外的深林中却亮起了三枚火光——这是待命观察的「家人」们在传递讯息。\n三枚火光，对应着最糟糕的事态：执律庭也盯上了这名目标，甚至已经派人上门。\n如果沿着原路撤离，与执律庭撞上的概率不小。一旦他们利用魔术师身份执行任务的事情暴露，不仅自己万劫不复，更有可能牵连身后的「家人」。\n书房外的人声越发嘈杂，想要以最快、最隐蔽的方式撤离，只能铤而走险。\n别馆依山而建，窗外就是悬崖，下方则是湍急的河流。\n琳妮特与林尼对视一眼，未发一言，紧紧抓着对方的手，从窗口跃下。\n「哗——」激震的水花猛撞在林尼身上。\n在落水之前，他拼命以自己的肩背承受冲击，再一次庇护了琳妮特。猛烈的冲击却也吞没了他的意识。\n琳妮特在惊慌中勉力抓住一段浮木，拖着昏迷的林尼挣扎上岸，不住咳水。\n强忍着肺部灼烧般的疼痛，琳妮特紧张地检查起林尼的状态：他的脸色苍白，双眸紧闭，不复往日神采。\n琳妮特紧抱林尼，以防他继续失温，同时警惕地观察起四周：这是一片伸手不见五指的深林，在夜色的遮蔽下，扭曲的树木更显狰狞。\n琳妮特低声呼唤着林尼的名字，希望他能像往常表演时一样，开着玩笑就站起身。但这一次，回应琳妮特的却只有沉默和他微弱的呼息。\n时隔多年，那一夜的孤独与恐惧，再度袭上心头。\n明明过了那么久，明明经历了那么多，明明以为自己已经有所成长。\n为什么还是和那一晚一样，只能在庇护下等待？只能在黑暗中颤抖？\n不该是这样的…明明已经携手缔造过那么多奇迹，明明已经一起战胜过那么多困境。\n…明明已经许愿过，要站在你身后，背靠着背，肩并着肩。\n执律庭的人或许就在近处逡巡，不能高声向「家人」呼救，也不能再做逗留。\n此刻琳妮特能做的，只有握紧林尼的手，将他扛上肩头。\n看不清前路的话，就用听的吧。\n她高高竖起耳朵，不放过任何一丝风声。\n风吹过树杈的声音、经过灌木的声音、拂过面颊的声音…逐渐在她的眼前绘出一副模糊的风景。\n琳妮特在黑暗中摸索前进，沿路荆棘刺痛肌肤，渗出的血染红衣襟。\n渐渐地，眼前的风景开始变得越发清晰。不知是因为耳朵适应了风声，还是眼睛适应了黑暗。她的脚步越加敏捷而坚定。\n在这片没有灯光的舞台上，在这场无人喝彩的演出中，琳妮特终于成为了主角。\n晨曦照进森林，琳妮特扛着林尼回到与「家人」们接头的营地，却遇见了意料之外的人物——他们的「父亲」，已在昨夜专程赶到。\n琳妮特用尽力气，从怀中取出已经濡湿的罪证。然而还未能交给「父亲」，就因体力不支，连带着林尼一起跌倒。\n「父亲」一把扶住两人，任由罪证落地，沾满泥泞。\n「好好睡一觉吧。你们已经带回…更珍贵的战利品了。」\n一枚神之眼，倒映着晨曦与双子的睡颜，在琳妮特腰间静静闪烁。"
      },
      "text": "角色/故事\n|角色详细=提起枫丹廷最有名气的魔术师，观众一定会想起舞台上神采飞扬的林尼。\n但提起枫丹廷最有名气的魔术助手，观众们就往往摸头不着，莫衷一是了。\n喝彩并非为她而起，掌声亦非为她而鸣。身为助手，她只会在必要的时机引开观众注意，再将高光时刻还予主角。\n无论是在台上还是台下，琳妮特总是习惯性地将自己藏在林尼身后，那一小块灯光与赞誉都照不进的影子里。\n对于一名魔术助手而言，保持低调是一种职业素养。\n对于「家」里的孩子而言…隐匿于影，更是一种生存之道。\n|角色故事1=琳妮特常把「待机」、「节能」之类的说辞挂在嘴边，借此规避不必要的麻烦。\n遇上不想干的杂务，如果说自己正在「发呆」，十有八九会招来一句「那不就是有空吗！」接着继续被强人所难。\n但如果一本正经地宣称自己正处于「待机模式」、必须「节约能量」，配合琳妮特雕塑般的表情，就足以令对方懵怔一时。\n趁着这个空当，琳妮特就可以顶着一副严肃面孔，平静从容地逃离现场了。\n这一出对付熟人并不好用，不过能与琳妮特相熟的人，大多清楚琳妮特怕麻烦的性格，更清楚…让她做杂务的后果。\n尽管嘴里常念一些机械专有名词，但琳妮特对机械知识的了解，恐怕也仅限于此。\n在琳妮特的家里流传着这样的劝诫：不要让琳妮特单独与洗碗机、吸尘器等任何一部机械同处一室。\n否则在第三方——往往是菲米尼——赶到之时，机械只会落得两种下场：\n一、机械坏得莫名其妙：洗碗机口吐白沫、吸尘器倒地抽搐…琳妮特一脸无辜地站在满地狼藉之间；\n二、机械安然无恙，杂务全无进度，琳妮特窝在角落里偷闲安睡。\n鉴于在开门前两种结果无法预测，且无论哪种都有害无益，琳妮特心安理得地告别了所有家务。\n不过说来也怪，明明不管多简单的机械都记不得操作、三两下就能弄坏…\n唯独在操纵魔术机关时，琳妮特却比林尼还要全神贯注，旷日经年，从不出错。\n|角色故事2=从某种角度来说，「魔术助手」是一个矛盾的职业。\n台上的喝彩与掌声，属于身为主角的魔术师；台下的鲜花与名利，也不曾眷顾主角的助手。\n然而一出精彩的表演，却又少不得助手的配合。\n身为舞台上最接近魔术师的人，助手清楚魔术师所有的隐秘，在危险的表演中，助手的一举一动更牵连着魔术师的生死。\n舞台上的魔术师与助手就如双面的镜子，一面向光，吸引观众的注意；一面朝暗，在背后完成手法，两面彼此轮转，变幻无常。\n要想配合得圆融如意，助手本人的魔术造诣，就不能比魔术师低多少。\n可有了这等技艺，又怎么会甘心久居人下？是以大多数学徒出身的助手，在学艺有成后就会自立门户，不会永远安于助手之位。\n林尼出道成名以后，也有不少名流看中了琳妮特身上的潜力，觉得她若独立出来，肯定能成为更耀眼的明星，甚至还有人想邀请她出演映影片的女主角。\n猫耳、少女、魔术师…光是这些噱头一堆，就足以赚满眼球！\n无奈琳妮特自己对这些盛情置若罔闻，不但拒绝了所有挖角…甚至连拒绝的理由也懒得编，所有回信都扔给林尼来写。\n这可愁苦了林尼，这些观众大多身份显赫，「父亲」大人吩咐过不能轻慢。\n如果被发现试图从林尼处挖角的信是由林尼本人回的，下次见面恐怕会相当尴尬。\n于是他只能模仿琳妮特的口吻，编出一封封的礼数周全，态度恳切的拒信。\n即使巧舌如林尼，要用琳妮特平日那副惜字如金的口吻写这种信，也是相当费心思的。\n每每写到心累手酸，看着一旁正悠然趴在沙发上的琳妮特，林尼也忍不住想想：要不然真让她去试试吧？换我做助手也行。\n「…别想。」琳妮特敏锐地捕捉到这一闪而过的念头，伸个懒腰翻身看向林尼，「我就喜欢当你的助手。」\n|角色故事3=泡茶是琳妮特为数不多的爱好之一。\n看着茶盏上氤氲的气旋，闻着淡雅的清香，一整天的疲惫都会烟消云散。\n每逢贵客上门，多是由林尼出面相谈，琳妮特以茶待客；家里办起茶话会来，也多是她来负责泡茶，其他家人负责说话。\n在旁人或高谈阔论，或清聊闲谈时，琳妮特总是坐在一边，双手捧杯，默默吹凉，小口啜饮。\n她的舌头天生敏感，喝不得太烫的茶水。\n但用温水冲茶，简直是暴殄天物；至于往茶里加冰、拿两个杯子来回倒茶降温之类的，更会被琳妮特斥为邪道。\n加冰会影响茶的浓度，倒茶会破坏口感层次…只有小口小口地吹凉，才能把握好最佳的温度，既不被烫着，又不失风味。\n等茶温降到可以入口，也不该急着饮尽。\n一些茶越是见底，风味越是浓郁，一口入喉总要先回味几分钟，才能继续品鉴。所以她喝起茶来总是慢条斯理。\n等到茶壶倒空，天也就差不多聊完了。\n至于剩下的一桌茶具…就交给别人收拾吧，免得又把洗碗机弄坏了。\n|角色故事4=曾有一位枫丹官员，想调查「布法蒂公馆」近几个月的资金流动。\n然而调查计划才刚拟出个草案，就被他的上司草草叫停。\n这位官员怎么也想不到，上司叫停调查是因为收到了一封信，随信还附了一组他与一位名媛幽会的画片。\n这名上司也怎么都想不到，这则秘密暴露的契机，仅仅是在一场魔术演出时，他掏出了一块不属于他夫人的手帕。\n当时他正感动于台上的精彩表演，却忽略了自暗处投来的另一道视线。\n这片刻的分神足够让琳妮特在对方毫无觉察的情况下，「偷走」他身上所有情报。\n人们会不自觉地暴露自己，服饰、眼神、肢体动作、甚至语气中的沉默…\n常人无法从中读出什么，是因为信息往往埋没于茫茫多的细节之中，而琳妮特却能以非同寻常的观察力，从中捕捉到关键。\n将无数看似琐碎的细节串联之后，就能引出对公馆有用的情报。\n一人在明，一人在暗，公馆的这对「眼睛」，已经从枫丹名流身上盗走无数隐秘。被盗者惘然不觉，宛如身处一场魔术。\n保持敏锐需要精神的绝对集中，因此工作中的琳妮特总是寡言少语，节省心力。\n即使是在日常休息，她也会习惯性地过滤掉各种无用信息。\n…只是这时候什么信息有用，什么无用，就全凭琳妮特的一己之好了。\n比如各种机械操作和家务技能，只要完全不去做家务，就可以理直气壮的置之脑后。\n又比如茶话会上的闲聊八卦，只要适当地接一句「原来如此」、「竟然是这样」、「然后呢」…就可以顺利推进对话。\n节能省力，颇合心意。\n|角色故事5=常有人以为，琳妮特的猫耳也是演出服的一部分。因为哥哥林尼与她流着同样的血，外表却与常人无异。\n可琳妮特多出的一对耳朵一条尾巴，却是实打实的长在身上，真得不能再真。\n据说这种类似猫的性状，往往会伴着血缘遗传，即便后代血脉日渐稀薄，偶尔也会出现「返祖现象」。\n年幼时的琳妮特，并不喜欢这份来自先祖的馈赠。\n总有好事的孩子，或有心或无意，指着它们问琳妮特：为什么你跟大家不一样？你跟林尼是不是亲生的兄妹？\n内向的琳妮特不知如何作答，林尼也不能总陪在她身边。每逢这时，她只能压着耳朵、卷起尾巴，蹲在角落里独自伤心。\n只有街头巷尾的流浪猫们会来安慰琳妮特，绕着她的脚踝轻蹭。\n不能带着这幅表情去见林尼。她心里很清楚。哥哥要操心的事已经很多了，不该再为这点幼稚的事情困扰。\n但强装无事也肯定会被他看穿，想要瞒过天才的魔术师，必须先瞒过自己。\n琳妮特抱起脚边的小猫，轻抚它背上的毛发。感受着它的呼吸，琳妮特的情绪渐渐缓和下来。\n小猫跳出了她的怀抱，她的脸上也已恢复了往日的平静。\n枫丹贵族中还有一些以追寻新奇为乐的败类。一场宴会上，一名「大人物」就相中了琳妮特的不同寻常。\n当时的养父不假思索地将她塞进了「大人物」的车里，不管她的反对，不顾她的挣扎，仿佛只是送出了一只会挠沙发的宠物猫。\n为什么是自己？为什么自己会长这对耳朵？\n令人窒息的孤独中，琳妮特终于压抑不住心中多年的积郁，痛苦地盖住了耳朵。\n「别再躲躲藏藏了，胆怯是无用的。」直到一个声音，与月光一起映入黑暗，「出来吧。想害你的人已经死了。」\n那声音冷酷而肃杀，却又有一种令人安心的魔力。琳妮特抬眼，望向日后的「父亲」。\n「不错的耳朵，可以用来监听。从今往后，学会利用它们吧。」\n「父亲」揉着琳妮特的耳朵，手法并不温柔，言辞并不温和，与那夜的月光一样清冷。\n也像月光一样，照亮一角黑暗。\n……\n「猫的耳朵向后翻折，往往是在恐惧或者警戒，向前竖起多半表示心情愉快…」\n林尼向布法蒂公馆的新成员科普猫的习性时，总会忍不住偷眼去看一旁的妹妹。\n琳妮特的耳朵正朝前竖着，偶尔向外扑闪。\n它们已经很久没再向后翻折了。\n|冒险笔记名称=「非自动」喂食机\n|冒险笔记=菲米尼帮忙订做的自动给食机关，用以应付家里越来越多的小动物。\n某场演出结束后，琳妮特在剧院后门发现了一口被遗弃的箱子。\n打开箱盖，几只不足月的幼猫惊惶地抬头，却饿得没有力气逃窜，只能紧张地盯着她的眼睛。\n琳妮特没说话，也没伸手惊扰，只是默默与它们对视。\n慢慢地，幼猫们似乎明白了琳妮特并无恶意，终于垂下了仰得酸痛的小脑袋。\n琳妮特这才抱起箱子，一箱小猫不吵不闹，安静地趴在箱底，等待面前的少女将它们带去新的「家庭」。\n关于是否收留这些小动物，家人们进行过一番小小的争论，一向寡言少语的琳妮特这时却一反常态，执意要留下它们。\n事情最后竟传到了「父亲」耳朵里，她一锤定音，要孩子们停止这番无聊的吵闹。\n「要养的自己去养就好了，记得自己管教好，别给其他人添麻烦。」\n沉默片刻，又补上一句：「如果在今年的冬天结束之前，还没教会它们怎么守规矩，就自己处理掉它们吧。」\n「父亲」如此表态，正反双方也都不好再说什么。至于教养它们的任务，则落到了琳妮特身上。\n鉴于琳妮特平日里总是一副怕麻烦的样子，菲米尼特意订做了一台自动喂食机。\n这台机器内置计时与称重机关，还有可以防潮的轮盘式粮箱，可以定时定量为小猫们提供各种食粮。\n这也成了少数在琳妮特手下幸存的机械之一，服役多年都没出过故障，内部结构更是焕然如新，只有出粮口下方的盘子有经常使用的痕迹。\n——因为琳妮特就没正经用过它。\n每个箱格里要加什么类型的食粮、如何设置供餐时间和供餐量…比起牢记这些，还是每天亲手准备猫食装进盘里比较方便。\n更何况，如果连喂食都交给机械的话…\n琳妮特蹲在「非自动」喂食机旁，一边帮吃饱喝足的猫顺毛，一边默默地想着。\n…又怎么能教好这些孩子呢？\n|神之眼=小时候，琳妮特常听林尼讲神之眼的故事。\n故事里的主角仿佛无所不能，勾勾手指就能卷起风暴，轻轻呵气就能吹散阴霾。\n那不是精心准备的魔术，而是货真价实的奇迹。\n如果我们也有神之眼就好了。彼时的琳妮特常想。\n能让魔术变成真正的魔法。能从帽子里变出果腹的食物、取暖的篝火。能让林尼不用总为了生计奔波。\n但神明并未垂听她的祈祷。后来的日子里，她和林尼继续流浪，在都市街头与贵族府邸间几经辗转，终于在「父亲」的庇护下寻得一隅落脚之地。\n两人深知这机会来之不易，熬过严苛的训练，彼此支撑着完成无数任务。\n现实早早地磨洗了童真，对神之眼的幻想也被遗忘在久远的过去。\n某次行动中，他们被派去一名贵族的山间别馆表演魔术，伺机盗取目标藏于书房的犯罪证据。\n任务本身再普通不过，进行得也很顺利。借演出的机会，两人在别馆的门窗上做了手脚。等到表演结束，再悄悄折返潜入，就能神不知鬼不觉地偷走罪证。\n然而就在他们得手之际，窗外的深林中却亮起了三枚火光——这是待命观察的「家人」们在传递讯息。\n三枚火光，对应着最糟糕的事态：执律庭也盯上了这名目标，甚至已经派人上门。\n如果沿着原路撤离，与执律庭撞上的概率不小。一旦他们利用魔术师身份执行任务的事情暴露，不仅自己万劫不复，更有可能牵连身后的「家人」。\n书房外的人声越发嘈杂，想要以最快、最隐蔽的方式撤离，只能铤而走险。\n别馆依山而建，窗外就是悬崖，下方则是湍急的河流。\n琳妮特与林尼对视一眼，未发一言，紧紧抓着对方的手，从窗口跃下。\n「哗——」激震的水花猛撞在林尼身上。\n在落水之前，他拼命以自己的肩背承受冲击，再一次庇护了琳妮特。猛烈的冲击却也吞没了他的意识。\n琳妮特在惊慌中勉力抓住一段浮木，拖着昏迷的林尼挣扎上岸，不住咳水。\n强忍着肺部灼烧般的疼痛，琳妮特紧张地检查起林尼的状态：他的脸色苍白，双眸紧闭，不复往日神采。\n琳妮特紧抱林尼，以防他继续失温，同时警惕地观察起四周：这是一片伸手不见五指的深林，在夜色的遮蔽下，扭曲的树木更显狰狞。\n琳妮特低声呼唤着林尼的名字，希望他能像往常表演时一样，开着玩笑就站起身。但这一次，回应琳妮特的却只有沉默和他微弱的呼息。\n时隔多年，那一夜的孤独与恐惧，再度袭上心头。\n明明过了那么久，明明经历了那么多，明明以为自己已经有所成长。\n为什么还是和那一晚一样，只能在庇护下等待？只能在黑暗中颤抖？\n不该是这样的…明明已经携手缔造过那么多奇迹，明明已经一起战胜过那么多困境。\n…明明已经许愿过，要站在你身后，背靠着背，肩并着肩。\n执律庭的人或许就在近处逡巡，不能高声向「家人」呼救，也不能再做逗留。\n此刻琳妮特能做的，只有握紧林尼的手，将他扛上肩头。\n看不清前路的话，就用听的吧。\n她高高竖起耳朵，不放过任何一丝风声。\n风吹过树杈的声音、经过灌木的声音、拂过面颊的声音…逐渐在她的眼前绘出一副模糊的风景。\n琳妮特在黑暗中摸索前进，沿路荆棘刺痛肌肤，渗出的血染红衣襟。\n渐渐地，眼前的风景开始变得越发清晰。不知是因为耳朵适应了风声，还是眼睛适应了黑暗。她的脚步越加敏捷而坚定。\n在这片没有灯光的舞台上，在这场无人喝彩的演出中，琳妮特终于成为了主角。\n晨曦照进森林，琳妮特扛着林尼回到与「家人」们接头的营地，却遇见了意料之外的人物——他们的「父亲」，已在昨夜专程赶到。\n琳妮特用尽力气，从怀中取出已经濡湿的罪证。然而还未能交给「父亲」，就因体力不支，连带着林尼一起跌倒。\n「父亲」一把扶住两人，任由罪证落地，沾满泥泞。\n「好好睡一觉吧。你们已经带回…更珍贵的战利品了。」\n一枚神之眼，倒映着晨曦与双子的睡颜，在琳妮特腰间静静闪烁。"
    },
    {
      "type": "template",
      "name": "角色/命之座",
      "args": [],
      "data": {
        "命之座1": "如影流露的冷刃",
        "命之座1效果": "谜影障身法的谜影突刺命中带有刺影征标的敌人时，将在敌人的位置生成风涡，牵引附近的敌人。",
        "命之座2": "层见叠出的谜象",
        "命之座2效果": "魔术·运变惊奇召唤的惊奇猫猫盒发射彩练术弹时，将额外发射一枚彩练术弹。",
        "命之座3": "倒错知能的视度",
        "命之座3效果": "魔术·运变惊奇的技能等级提升3级。\n至多提升至15级。",
        "命之座4": "灵犀默应的配合",
        "命之座4效果": "谜影障身法的可使用次数增加1次。",
        "命之座5": "暗昧遮目的障法",
        "命之座5效果": "谜影障身法的技能等级提升3级。\n至多提升至15级。",
        "命之座6": "示辨真意的眼",
        "命之座6效果": "琳妮特施放谜影障身法的谜影突刺时，将获得风元素附魔，风元素伤害加成提升20%，持续6秒。"
      },
      "text": "角色/命之座\n|命之座1=如影流露的冷刃\n|命之座1效果=谜影障身法的谜影突刺命中带有刺影征标的敌人时，将在敌人的位置生成风涡，牵引附近的敌人。\n|命之座2=层见叠出的谜象\n|命之座2效果=魔术·运变惊奇召唤的惊奇猫猫盒发射彩练术弹时，将额外发射一枚彩练术弹。\n|命之座3=倒错知能的视度\n|命之座3效果=魔术·运变惊奇的技能等级提升3级。\n至多提升至15级。\n|命之座4=灵犀默应的配合\n|命之座4效果=谜影障身法的可使用次数增加1次。\n|命之座5=暗昧遮目的障法\n|命之座5效果=谜影障身法的技能等级提升3级。\n至多提升至15级。\n|命之座6=示辨真意的眼\n|命之座6效果=琳妮特施放谜影障身法的谜影突刺时，将获得风元素附魔，风元素伤害加成提升20%，持续6秒。"
    },
    {
      "type": "heading",
      "level": 2,
      "text": "天赋"
    },
    {
      "type": "template",
      "name": "角色技能/1",
      "args": [
        "迅捷礼刺剑"
      ],
      "data": {},
      "text": "角色技能/1|迅捷礼刺剑"
    },
    {
      "type": "template",
      "name": "角色技能/2",
      "args": [
        "谜影障身法"
      ],
      "data": {},
      "text": "角色技能/2|谜影障身法"
    },
    {
      "type": "template",
      "name": "角色技能/3",
      "args": [
        "魔术·运变惊奇"
      ],
      "data": {},
      "text": "角色技能/3|魔术·运变惊奇"
    },
    {
      "type": "template",
      "name": "角色技能/4",
      "args": [
        "巧施协同"
      ],
      "data": {},
      "text": "角色技能/4|巧施协同"
    },
    {
      "type": "template",
      "name": "角色技能/4",
      "args": [
        "道具完备"
      ],
      "data": {},
      "text": "角色技能/4|道具完备"
    },
    {
      "type": "template",
      "name": "角色技能/4",
      "args": [
        "点位记忆法"
      ],
      "data": {},
      "text": "角色技能/4|点位记忆法"
    },
    {
      "type": "template",
      "name": "天赋技能",
      "args": [
        "7"
      ],
      "data": {
        "技能名": "迅捷礼刺剑",
        "描述": "普通攻击\n进行至多四段的连续剑击。\n\n重击\n消耗一定体力，瞬间向前方挥出两剑。\n\n下落攻击\n从空中下坠冲击地面，攻击下落路径上的敌人，并在落地时造成范围伤害。",
        "GIF": "1",
        "属性1": "一段伤害",
        "属性1LV1": "43.1%",
        "属性1LV2": "46.6%",
        "属性1LV3": "50.1%",
        "属性1LV4": "55.1%",
        "属性1LV5": "58.6%",
        "属性1LV6": "62.6%",
        "属性1LV7": "68.1%",
        "属性1LV8": "73.6%",
        "属性1LV9": "79.2%",
        "属性1LV10": "85.2%",
        "属性1LV11": "91.2%",
        "属性1LV12": "",
        "属性1LV13": "",
        "属性1LV14": "",
        "属性1LV15": "",
        "属性2": "二段伤害",
        "属性2LV1": "37.6%",
        "属性2LV2": "40.7%",
        "属性2LV3": "43.7%",
        "属性2LV4": "48.1%",
        "属性2LV5": "51.2%",
        "属性2LV6": "54.7%",
        "属性2LV7": "59.5%",
        "属性2LV8": "64.3%",
        "属性2LV9": "69.1%",
        "属性2LV10": "74.3%",
        "属性2LV11": "79.6%",
        "属性2LV12": "",
        "属性2LV13": "",
        "属性2LV14": "",
        "属性2LV15": "",
        "属性3": "三段伤害",
        "属性3LV1": "27.9%+21.6%",
        "属性3LV2": "30.1%+23.4%",
        "属性3LV3": "32.4%+25.1%",
        "属性3LV4": "35.6%+27.6%",
        "属性3LV5": "37.9%+29.4%",
        "属性3LV6": "40.5%+31.4%",
        "属性3LV7": "44.1%+34.1%",
        "属性3LV8": "47.6%+36.9%",
        "属性3LV9": "51.2%+39.7%",
        "属性3LV10": "55.1%+42.7%",
        "属性3LV11": "59.0%+45.7%",
        "属性3LV12": "",
        "属性3LV13": "",
        "属性3LV14": "",
        "属性3LV15": "",
        "属性4": "四段伤害",
        "属性4LV1": "63.2%",
        "属性4LV2": "68.3%",
        "属性4LV3": "73.4%",
        "属性4LV4": "80.8%",
        "属性4LV5": "85.9%",
        "属性4LV6": "91.8%",
        "属性4LV7": "99.9%",
        "属性4LV8": "107.9%",
        "属性4LV9": "116.0%",
        "属性4LV10": "124.8%",
        "属性4LV11": "133.7%",
        "属性4LV12": "",
        "属性4LV13": "",
        "属性4LV14": "",
        "属性4LV15": "",
        "属性5": "重击伤害",
        "属性5LV1": "44.2%+61.4%",
        "属性5LV2": "47.8%+66.4%",
        "属性5LV3": "51.4%+71.4%",
        "属性5LV4": "56.5%+78.5%",
        "属性5LV5": "60.1%+83.5%",
        "属性5LV6": "64.3%+89.3%",
        "属性5LV7": "69.9%+97.1%",
        "属性5LV8": "75.6%+105.0%",
        "属性5LV9": "81.2%+112.8%",
        "属性5LV10": "87.4%+121.4%",
        "属性5LV11": "93.6%+130.0%",
        "属性5LV12": "",
        "属性5LV13": "",
        "属性5LV14": "",
        "属性5LV15": "",
        "属性6": "重击体力消耗",
        "属性6LV1": "20.0点",
        "属性6LV2": "20.0点",
        "属性6LV3": "20.0点",
        "属性6LV4": "20.0点",
        "属性6LV5": "20.0点",
        "属性6LV6": "20.0点",
        "属性6LV7": "20.0点",
        "属性6LV8": "20.0点",
        "属性6LV9": "20.0点",
        "属性6LV10": "20.0点",
        "属性6LV11": "20.0点",
        "属性6LV12": "",
        "属性6LV13": "",
        "属性6LV14": "",
        "属性6LV15": "",
        "属性7": "下坠期间伤害",
        "属性7LV1": "63.9%",
        "属性7LV2": "69.1%",
        "属性7LV3": "74.3%",
        "属性7LV4": "82.0%",
        "属性7LV5": "87.0%",
        "属性7LV6": "92.9%",
        "属性7LV7": "101.1%",
        "属性7LV8": "109.3%",
        "属性7LV9": "117.5%",
        "属性7LV10": "126.4%",
        "属性7LV11": "135.3%",
        "属性7LV12": "",
        "属性7LV13": "",
        "属性7LV14": "",
        "属性7LV15": "",
        "属性8": "低空/高空坠地冲击伤害",
        "属性8LV1": "128%/160%",
        "属性8LV2": "138%/173%",
        "属性8LV3": "149%/186%",
        "属性8LV4": "164%/204%",
        "属性8LV5": "174%/217%",
        "属性8LV6": "186%/232%",
        "属性8LV7": "202%/253%",
        "属性8LV8": "219%/273%",
        "属性8LV9": "235%/293%",
        "属性8LV10": "253%/316%",
        "属性8LV11": "270.5%/337.9%",
        "属性8LV12": "",
        "属性8LV13": "",
        "属性8LV14": "",
        "属性8LV15": ""
      },
      "text": "天赋技能|7\n|技能名=迅捷礼刺剑\n|描述=普通攻击\n进行至多四段的连续剑击。\n\n重击\n消耗一定体力，瞬间向前方挥出两剑。\n\n下落攻击\n从空中下坠冲击地面，攻击下落路径上的敌人，并在落地时造成范围伤害。\n|GIF=1\n|属性1=一段伤害\n|属性1LV1=43.1%\n|属性1LV2=46.6%\n|属性1LV3=50.1%\n|属性1LV4=55.1%\n|属性1LV5=58.6%\n|属性1LV6=62.6%\n|属性1LV7=68.1%\n|属性1LV8=73.6%\n|属性1LV9=79.2%\n|属性1LV10=85.2%\n|属性1LV11=91.2%\n|属性1LV12=\n|属性1LV13=\n|属性1LV14=\n|属性1LV15=\n|属性2=二段伤害\n|属性2LV1=37.6%\n|属性2LV2=40.7%\n|属性2LV3=43.7%\n|属性2LV4=48.1%\n|属性2LV5=51.2%\n|属性2LV6=54.7%\n|属性2LV7=59.5%\n|属性2LV8=64.3%\n|属性2LV9=69.1%\n|属性2LV10=74.3%\n|属性2LV11=79.6%\n|属性2LV12=\n|属性2LV13=\n|属性2LV14=\n|属性2LV15=\n|属性3=三段伤害\n|属性3LV1=27.9%+21.6%\n|属性3LV2=30.1%+23.4%\n|属性3LV3=32.4%+25.1%\n|属性3LV4=35.6%+27.6%\n|属性3LV5=37.9%+29.4%\n|属性3LV6=40.5%+31.4%\n|属性3LV7=44.1%+34.1%\n|属性3LV8=47.6%+36.9%\n|属性3LV9=51.2%+39.7%\n|属性3LV10=55.1%+42.7%\n|属性3LV11=59.0%+45.7%\n|属性3LV12=\n|属性3LV13=\n|属性3LV14=\n|属性3LV15=\n|属性4=四段伤害\n|属性4LV1=63.2%\n|属性4LV2=68.3%\n|属性4LV3=73.4%\n|属性4LV4=80.8%\n|属性4LV5=85.9%\n|属性4LV6=91.8%\n|属性4LV7=99.9%\n|属性4LV8=107.9%\n|属性4LV9=116.0%\n|属性4LV10=124.8%\n|属性4LV11=133.7%\n|属性4LV12=\n|属性4LV13=\n|属性4LV14=\n|属性4LV15=\n|属性5=重击伤害\n|属性5LV1=44.2%+61.4%\n|属性5LV2=47.8%+66.4%\n|属性5LV3=51.4%+71.4%\n|属性5LV4=56.5%+78.5%\n|属性5LV5=60.1%+83.5%\n|属性5LV6=64.3%+89.3%\n|属性5LV7=69.9%+97.1%\n|属性5LV8=75.6%+105.0%\n|属性5LV9=81.2%+112.8%\n|属性5LV10=87.4%+121.4%\n|属性5LV11=93.6%+130.0%\n|属性5LV12=\n|属性5LV13=\n|属性5LV14=\n|属性5LV15=\n|属性6=重击体力消耗\n|属性6LV1=20.0点\n|属性6LV2=20.0点\n|属性6LV3=20.0点\n|属性6LV4=20.0点\n|属性6LV5=20.0点\n|属性6LV6=20.0点\n|属性6LV7=20.0点\n|属性6LV8=20.0点\n|属性6LV9=20.0点\n|属性6LV10=20.0点\n|属性6LV11=20.0点\n|属性6LV12=\n|属性6LV13=\n|属性6LV14=\n|属性6LV15=\n|属性7=下坠期间伤害\n|属性7LV1=63.9%\n|属性7LV2=69.1%\n|属性7LV3=74.3%\n|属性7LV4=82.0%\n|属性7LV5=87.0%\n|属性7LV6=92.9%\n|属性7LV7=101.1%\n|属性7LV8=109.3%\n|属性7LV9=117.5%\n|属性7LV10=126.4%\n|属性7LV11=135.3%\n|属性7LV12=\n|属性7LV13=\n|属性7LV14=\n|属性7LV15=\n|属性8=低空/高空坠地冲击伤害\n|属性8LV1=128%/160%\n|属性8LV2=138%/173%\n|属性8LV3=149%/186%\n|属性8LV4=164%/204%\n|属性8LV5=174%/217%\n|属性8LV6=186%/232%\n|属性8LV7=202%/253%\n|属性8LV8=219%/273%\n|属性8LV9=235%/293%\n|属性8LV10=253%/316%\n|属性8LV11=270.5%/337.9%\n|属性8LV12=\n|属性8LV13=\n|属性8LV14=\n|属性8LV15="
    },
    {
      "type": "template",
      "name": "天赋技能",
      "args": [
        "7"
      ],
      "data": {
        "技能名": "谜影障身法",
        "描述": "挥舞斗篷，击出谜影突刺，造成风元素伤害。\n谜影突刺命中敌人时，将为琳妮特恢复生命值，回复量基于琳妮特的生命值上限，并在此后的4秒内，每秒将消耗一定的生命值。\n依据点按、长按，以不同的方式击出谜影突刺。\n\n点按\n迅速击出谜影突刺。\n\n长按\n琳妮特以「谜身影盗」的姿态疾走，并对附近的敌人施加「刺影征标」。期间可以控制疾走的方向，并能通过再次施放技能，提前结束疾走状态。\n疾走结束时，琳妮特将击出谜影突刺。若附近存在具有刺影征标的敌人，琳妮特将在击出谜影突刺前高速闪掠接近该敌人。\n\n同时至多有一名敌人具有琳妮特自身施加的刺影征标。与具有刺影征标的敌人距离过远时，将移除该刺影征标。\n\n始基力：荒性\n每隔一段时间，琳妮特击出谜影突刺时，将唤出流涌之刃，造成具有荒性的风元素伤害。\n\n「现在就将视线转回台上，继续观赏表演吧。当我再次出现，就会是在你意想不到的地方了。」",
        "GIF": "1",
        "属性1": "谜影突刺伤害",
        "属性1LV1": "268.0%",
        "属性1LV2": "288.1%",
        "属性1LV3": "308.2%",
        "属性1LV4": "335.0%",
        "属性1LV5": "355.1%",
        "属性1LV6": "375.2%",
        "属性1LV7": "402.0%",
        "属性1LV8": "428.8%",
        "属性1LV9": "455.6%",
        "属性1LV10": "482.4%",
        "属性1LV11": "509.2%",
        "属性1LV12": "536.0%",
        "属性1LV13": "569.5%",
        "属性1LV14": "",
        "属性1LV15": "",
        "属性2": "流涌之刃伤害",
        "属性2LV1": "31.2%",
        "属性2LV2": "33.5%",
        "属性2LV3": "35.9%",
        "属性2LV4": "39.0%",
        "属性2LV5": "41.3%",
        "属性2LV6": "43.7%",
        "属性2LV7": "46.8%",
        "属性2LV8": "49.9%",
        "属性2LV9": "53.0%",
        "属性2LV10": "56.2%",
        "属性2LV11": "59.3%",
        "属性2LV12": "62.4%",
        "属性2LV13": "66.3%",
        "属性2LV14": "",
        "属性2LV15": "",
        "属性3": "流涌之刃间隔",
        "属性3LV1": "10.0秒",
        "属性3LV2": "10.0秒",
        "属性3LV3": "10.0秒",
        "属性3LV4": "10.0秒",
        "属性3LV5": "10.0秒",
        "属性3LV6": "10.0秒",
        "属性3LV7": "10.0秒",
        "属性3LV8": "10.0秒",
        "属性3LV9": "10.0秒",
        "属性3LV10": "10.0秒",
        "属性3LV11": "10.0秒",
        "属性3LV12": "10.0秒",
        "属性3LV13": "10.0秒",
        "属性3LV14": "",
        "属性3LV15": "",
        "属性4": "命中治疗量",
        "属性4LV1": "25%生命值上限",
        "属性4LV2": "25%生命值上限",
        "属性4LV3": "25%生命值上限",
        "属性4LV4": "25%生命值上限",
        "属性4LV5": "25%生命值上限",
        "属性4LV6": "25%生命值上限",
        "属性4LV7": "25%生命值上限",
        "属性4LV8": "25%生命值上限",
        "属性4LV9": "25%生命值上限",
        "属性4LV10": "25%生命值上限",
        "属性4LV11": "25%生命值上限",
        "属性4LV12": "25%生命值上限",
        "属性4LV13": "25%生命值上限",
        "属性4LV14": "",
        "属性4LV15": "",
        "属性5": "生命值消耗",
        "属性5LV1": "6%当前生命值/秒",
        "属性5LV2": "6%当前生命值/秒",
        "属性5LV3": "6%当前生命值/秒",
        "属性5LV4": "6%当前生命值/秒",
        "属性5LV5": "6%当前生命值/秒",
        "属性5LV6": "6%当前生命值/秒",
        "属性5LV7": "6%当前生命值/秒",
        "属性5LV8": "6%当前生命值/秒",
        "属性5LV9": "6%当前生命值/秒",
        "属性5LV10": "6%当前生命值/秒",
        "属性5LV11": "6%当前生命值/秒",
        "属性5LV12": "6%当前生命值/秒",
        "属性5LV13": "6%当前生命值/秒",
        "属性5LV14": "",
        "属性5LV15": "",
        "属性6": "长按最大持续时间",
        "属性6LV1": "2.5秒",
        "属性6LV2": "2.5秒",
        "属性6LV3": "2.5秒",
        "属性6LV4": "2.5秒",
        "属性6LV5": "2.5秒",
        "属性6LV6": "2.5秒",
        "属性6LV7": "2.5秒",
        "属性6LV8": "2.5秒",
        "属性6LV9": "2.5秒",
        "属性6LV10": "2.5秒",
        "属性6LV11": "2.5秒",
        "属性6LV12": "2.5秒",
        "属性6LV13": "2.5秒",
        "属性6LV14": "",
        "属性6LV15": "",
        "属性7": "冷却时间",
        "属性7LV1": "12.0秒",
        "属性7LV2": "12.0秒",
        "属性7LV3": "12.0秒",
        "属性7LV4": "12.0秒",
        "属性7LV5": "12.0秒",
        "属性7LV6": "12.0秒",
        "属性7LV7": "12.0秒",
        "属性7LV8": "12.0秒",
        "属性7LV9": "12.0秒",
        "属性7LV10": "12.0秒",
        "属性7LV11": "12.0秒",
        "属性7LV12": "12.0秒",
        "属性7LV13": "12.0秒",
        "属性7LV14": "",
        "属性7LV15": ""
      },
      "text": "天赋技能|7\n|技能名=谜影障身法\n|描述=挥舞斗篷，击出谜影突刺，造成风元素伤害。\n谜影突刺命中敌人时，将为琳妮特恢复生命值，回复量基于琳妮特的生命值上限，并在此后的4秒内，每秒将消耗一定的生命值。\n依据点按、长按，以不同的方式击出谜影突刺。\n\n点按\n迅速击出谜影突刺。\n\n长按\n琳妮特以「谜身影盗」的姿态疾走，并对附近的敌人施加「刺影征标」。期间可以控制疾走的方向，并能通过再次施放技能，提前结束疾走状态。\n疾走结束时，琳妮特将击出谜影突刺。若附近存在具有刺影征标的敌人，琳妮特将在击出谜影突刺前高速闪掠接近该敌人。\n\n同时至多有一名敌人具有琳妮特自身施加的刺影征标。与具有刺影征标的敌人距离过远时，将移除该刺影征标。\n\n始基力：荒性\n每隔一段时间，琳妮特击出谜影突刺时，将唤出流涌之刃，造成具有荒性的风元素伤害。\n\n「现在就将视线转回台上，继续观赏表演吧。当我再次出现，就会是在你意想不到的地方了。」\n|GIF=1\n|属性1=谜影突刺伤害\n|属性1LV1=268.0%\n|属性1LV2=288.1%\n|属性1LV3=308.2%\n|属性1LV4=335.0%\n|属性1LV5=355.1%\n|属性1LV6=375.2%\n|属性1LV7=402.0%\n|属性1LV8=428.8%\n|属性1LV9=455.6%\n|属性1LV10=482.4%\n|属性1LV11=509.2%\n|属性1LV12=536.0%\n|属性1LV13=569.5%\n|属性1LV14=\n|属性1LV15=\n|属性2=流涌之刃伤害\n|属性2LV1=31.2%\n|属性2LV2=33.5%\n|属性2LV3=35.9%\n|属性2LV4=39.0%\n|属性2LV5=41.3%\n|属性2LV6=43.7%\n|属性2LV7=46.8%\n|属性2LV8=49.9%\n|属性2LV9=53.0%\n|属性2LV10=56.2%\n|属性2LV11=59.3%\n|属性2LV12=62.4%\n|属性2LV13=66.3%\n|属性2LV14=\n|属性2LV15=\n|属性3=流涌之刃间隔\n|属性3LV1=10.0秒\n|属性3LV2=10.0秒\n|属性3LV3=10.0秒\n|属性3LV4=10.0秒\n|属性3LV5=10.0秒\n|属性3LV6=10.0秒\n|属性3LV7=10.0秒\n|属性3LV8=10.0秒\n|属性3LV9=10.0秒\n|属性3LV10=10.0秒\n|属性3LV11=10.0秒\n|属性3LV12=10.0秒\n|属性3LV13=10.0秒\n|属性3LV14=\n|属性3LV15=\n|属性4=命中治疗量\n|属性4LV1=25%生命值上限\n|属性4LV2=25%生命值上限\n|属性4LV3=25%生命值上限\n|属性4LV4=25%生命值上限\n|属性4LV5=25%生命值上限\n|属性4LV6=25%生命值上限\n|属性4LV7=25%生命值上限\n|属性4LV8=25%生命值上限\n|属性4LV9=25%生命值上限\n|属性4LV10=25%生命值上限\n|属性4LV11=25%生命值上限\n|属性4LV12=25%生命值上限\n|属性4LV13=25%生命值上限\n|属性4LV14=\n|属性4LV15=\n|属性5=生命值消耗\n|属性5LV1=6%当前生命值/秒\n|属性5LV2=6%当前生命值/秒\n|属性5LV3=6%当前生命值/秒\n|属性5LV4=6%当前生命值/秒\n|属性5LV5=6%当前生命值/秒\n|属性5LV6=6%当前生命值/秒\n|属性5LV7=6%当前生命值/秒\n|属性5LV8=6%当前生命值/秒\n|属性5LV9=6%当前生命值/秒\n|属性5LV10=6%当前生命值/秒\n|属性5LV11=6%当前生命值/秒\n|属性5LV12=6%当前生命值/秒\n|属性5LV13=6%当前生命值/秒\n|属性5LV14=\n|属性5LV15=\n|属性6=长按最大持续时间\n|属性6LV1=2.5秒\n|属性6LV2=2.5秒\n|属性6LV3=2.5秒\n|属性6LV4=2.5秒\n|属性6LV5=2.5秒\n|属性6LV6=2.5秒\n|属性6LV7=2.5秒\n|属性6LV8=2.5秒\n|属性6LV9=2.5秒\n|属性6LV10=2.5秒\n|属性6LV11=2.5秒\n|属性6LV12=2.5秒\n|属性6LV13=2.5秒\n|属性6LV14=\n|属性6LV15=\n|属性7=冷却时间\n|属性7LV1=12.0秒\n|属性7LV2=12.0秒\n|属性7LV3=12.0秒\n|属性7LV4=12.0秒\n|属性7LV5=12.0秒\n|属性7LV6=12.0秒\n|属性7LV7=12.0秒\n|属性7LV8=12.0秒\n|属性7LV9=12.0秒\n|属性7LV10=12.0秒\n|属性7LV11=12.0秒\n|属性7LV12=12.0秒\n|属性7LV13=12.0秒\n|属性7LV14=\n|属性7LV15="
    },
    {
      "type": "text",
      "text": "产球情况请参考元素能量学/角色数据。"
    },
    {
      "type": "template",
      "name": "天赋技能",
      "args": [
        "7"
      ],
      "data": {
        "技能名": "魔术·运变惊奇",
        "描述": "琳妮特高举斗篷造成风元素范围伤害，用惊人的手法变出巨大的惊奇猫猫盒！\n\n惊奇猫猫盒\n\n*能够持续嘲讽周围的敌人，吸引敌人攻击；\n\n*将周期性对附近的敌人造成风元素伤害；\n\n*惊奇猫猫盒接触了水元素/火元素/冰元素/雷元素，则会获得对应元素属性，周期性对附近的敌人追加发射彩练术弹，造成该元素的伤害。\n\n元素转化在技能持续期间仅会发生一次。\n\n「就看向这个方向，看仔细。这是独属于我们的，奇迹时刻。」",
        "GIF": "1",
        "属性1": "技能伤害",
        "属性1LV1": "83.2%",
        "属性1LV2": "89.4%",
        "属性1LV3": "95.7%",
        "属性1LV4": "104.0%",
        "属性1LV5": "110.2%",
        "属性1LV6": "116.5%",
        "属性1LV7": "124.8%",
        "属性1LV8": "133.1%",
        "属性1LV9": "141.4%",
        "属性1LV10": "149.8%",
        "属性1LV11": "158.1%",
        "属性1LV12": "166.4%",
        "属性1LV13": "176.8%",
        "属性1LV14": "",
        "属性1LV15": "",
        "属性2": "惊奇猫猫盒伤害",
        "属性2LV1": "51.2%",
        "属性2LV2": "55.0%",
        "属性2LV3": "58.9%",
        "属性2LV4": "64.0%",
        "属性2LV5": "67.8%",
        "属性2LV6": "71.7%",
        "属性2LV7": "76.8%",
        "属性2LV8": "81.9%",
        "属性2LV9": "87.0%",
        "属性2LV10": "92.2%",
        "属性2LV11": "97.3%",
        "属性2LV12": "102.4%",
        "属性2LV13": "108.8%",
        "属性2LV14": "",
        "属性2LV15": "",
        "属性3": "彩练术弹伤害",
        "属性3LV1": "45.6%",
        "属性3LV2": "49.0%",
        "属性3LV3": "52.4%",
        "属性3LV4": "57.0%",
        "属性3LV5": "60.4%",
        "属性3LV6": "63.8%",
        "属性3LV7": "68.4%",
        "属性3LV8": "73.0%",
        "属性3LV9": "77.5%",
        "属性3LV10": "82.1%",
        "属性3LV11": "86.6%",
        "属性3LV12": "91.2%",
        "属性3LV13": "96.9%",
        "属性3LV14": "",
        "属性3LV15": "",
        "属性4": "惊奇猫猫盒持续时间",
        "属性4LV1": "12.0秒",
        "属性4LV2": "12.0秒",
        "属性4LV3": "12.0秒",
        "属性4LV4": "12.0秒",
        "属性4LV5": "12.0秒",
        "属性4LV6": "12.0秒",
        "属性4LV7": "12.0秒",
        "属性4LV8": "12.0秒",
        "属性4LV9": "12.0秒",
        "属性4LV10": "12.0秒",
        "属性4LV11": "12.0秒",
        "属性4LV12": "12.0秒",
        "属性4LV13": "12.0秒",
        "属性4LV14": "",
        "属性4LV15": "",
        "属性5": "冷却时间",
        "属性5LV1": "18.0秒",
        "属性5LV2": "18.0秒",
        "属性5LV3": "18.0秒",
        "属性5LV4": "18.0秒",
        "属性5LV5": "18.0秒",
        "属性5LV6": "18.0秒",
        "属性5LV7": "18.0秒",
        "属性5LV8": "18.0秒",
        "属性5LV9": "18.0秒",
        "属性5LV10": "18.0秒",
        "属性5LV11": "18.0秒",
        "属性5LV12": "18.0秒",
        "属性5LV13": "18.0秒",
        "属性5LV14": "",
        "属性5LV15": "",
        "属性6": "元素能量",
        "属性6LV1": "70",
        "属性6LV2": "70",
        "属性6LV3": "70",
        "属性6LV4": "70",
        "属性6LV5": "70",
        "属性6LV6": "70",
        "属性6LV7": "70",
        "属性6LV8": "70",
        "属性6LV9": "70",
        "属性6LV10": "70",
        "属性6LV11": "70",
        "属性6LV12": "70",
        "属性6LV13": "70",
        "属性6LV14": "",
        "属性6LV15": "",
        "属性7": "",
        "属性7LV1": "",
        "属性7LV2": "",
        "属性7LV3": "",
        "属性7LV4": "",
        "属性7LV5": "",
        "属性7LV6": "",
        "属性7LV7": "",
        "属性7LV8": "",
        "属性7LV9": "",
        "属性7LV10": "",
        "属性7LV11": "",
        "属性7LV12": "",
        "属性7LV13": "",
        "属性7LV14": "",
        "属性7LV15": ""
      },
      "text": "天赋技能|7\n|技能名=魔术·运变惊奇\n|描述=琳妮特高举斗篷造成风元素范围伤害，用惊人的手法变出巨大的惊奇猫猫盒！\n\n惊奇猫猫盒\n\n*能够持续嘲讽周围的敌人，吸引敌人攻击；\n\n*将周期性对附近的敌人造成风元素伤害；\n\n*惊奇猫猫盒接触了水元素/火元素/冰元素/雷元素，则会获得对应元素属性，周期性对附近的敌人追加发射彩练术弹，造成该元素的伤害。\n\n元素转化在技能持续期间仅会发生一次。\n\n「就看向这个方向，看仔细。这是独属于我们的，奇迹时刻。」\n|GIF=1\n|属性1=技能伤害\n|属性1LV1=83.2%\n|属性1LV2=89.4%\n|属性1LV3=95.7%\n|属性1LV4=104.0%\n|属性1LV5=110.2%\n|属性1LV6=116.5%\n|属性1LV7=124.8%\n|属性1LV8=133.1%\n|属性1LV9=141.4%\n|属性1LV10=149.8%\n|属性1LV11=158.1%\n|属性1LV12=166.4%\n|属性1LV13=176.8%\n|属性1LV14=\n|属性1LV15=\n|属性2=惊奇猫猫盒伤害\n|属性2LV1=51.2%\n|属性2LV2=55.0%\n|属性2LV3=58.9%\n|属性2LV4=64.0%\n|属性2LV5=67.8%\n|属性2LV6=71.7%\n|属性2LV7=76.8%\n|属性2LV8=81.9%\n|属性2LV9=87.0%\n|属性2LV10=92.2%\n|属性2LV11=97.3%\n|属性2LV12=102.4%\n|属性2LV13=108.8%\n|属性2LV14=\n|属性2LV15=\n|属性3=彩练术弹伤害\n|属性3LV1=45.6%\n|属性3LV2=49.0%\n|属性3LV3=52.4%\n|属性3LV4=57.0%\n|属性3LV5=60.4%\n|属性3LV6=63.8%\n|属性3LV7=68.4%\n|属性3LV8=73.0%\n|属性3LV9=77.5%\n|属性3LV10=82.1%\n|属性3LV11=86.6%\n|属性3LV12=91.2%\n|属性3LV13=96.9%\n|属性3LV14=\n|属性3LV15=\n|属性4=惊奇猫猫盒持续时间\n|属性4LV1=12.0秒\n|属性4LV2=12.0秒\n|属性4LV3=12.0秒\n|属性4LV4=12.0秒\n|属性4LV5=12.0秒\n|属性4LV6=12.0秒\n|属性4LV7=12.0秒\n|属性4LV8=12.0秒\n|属性4LV9=12.0秒\n|属性4LV10=12.0秒\n|属性4LV11=12.0秒\n|属性4LV12=12.0秒\n|属性4LV13=12.0秒\n|属性4LV14=\n|属性4LV15=\n|属性5=冷却时间\n|属性5LV1=18.0秒\n|属性5LV2=18.0秒\n|属性5LV3=18.0秒\n|属性5LV4=18.0秒\n|属性5LV5=18.0秒\n|属性5LV6=18.0秒\n|属性5LV7=18.0秒\n|属性5LV8=18.0秒\n|属性5LV9=18.0秒\n|属性5LV10=18.0秒\n|属性5LV11=18.0秒\n|属性5LV12=18.0秒\n|属性5LV13=18.0秒\n|属性5LV14=\n|属性5LV15=\n|属性6=元素能量\n|属性6LV1=70\n|属性6LV2=70\n|属性6LV3=70\n|属性6LV4=70\n|属性6LV5=70\n|属性6LV6=70\n|属性6LV7=70\n|属性6LV8=70\n|属性6LV9=70\n|属性6LV10=70\n|属性6LV11=70\n|属性6LV12=70\n|属性6LV13=70\n|属性6LV14=\n|属性6LV15=\n|属性7=\n|属性7LV1=\n|属性7LV2=\n|属性7LV3=\n|属性7LV4=\n|属性7LV5=\n|属性7LV6=\n|属性7LV7=\n|属性7LV8=\n|属性7LV9=\n|属性7LV10=\n|属性7LV11=\n|属性7LV12=\n|属性7LV13=\n|属性7LV14=\n|属性7LV15="
    },
    {
      "type": "template",
      "name": "天赋技能",
      "args": [
        "0",
        "解锁1"
      ],
      "data": {
        "技能名": "巧施协同",
        "描述": "施放魔术·运变惊奇后的10秒内，队伍中分别存在1/2/3/4种元素类型的角色时，队伍中所有角色的攻击力分别提升8%/12%/16%/20%。"
      },
      "text": "天赋技能|0|解锁1\n|技能名=巧施协同\n|描述=施放魔术·运变惊奇后的10秒内，队伍中分别存在1/2/3/4种元素类型的角色时，队伍中所有角色的攻击力分别提升8%/12%/16%/20%。"
    },
    {
      "type": "template",
      "name": "天赋技能",
      "args": [
        "0",
        "解锁2"
      ],
      "data": {
        "技能名": "道具完备",
        "描述": "魔术·运变惊奇召唤的惊奇猫猫盒发生了元素转化后，琳妮特元素爆发造成的伤害提升15%，效果持续至该惊奇猫猫盒持续时间结束。"
      },
      "text": "天赋技能|0|解锁2\n|技能名=道具完备\n|描述=魔术·运变惊奇召唤的惊奇猫猫盒发生了元素转化后，琳妮特元素爆发造成的伤害提升15%，效果持续至该惊奇猫猫盒持续时间结束。"
    },
    {
      "type": "template",
      "name": "天赋技能",
      "args": [
        "0"
      ],
      "data": {
        "技能名": "点位记忆法",
        "描述": "在小地图上显示周围复苏水团的位置，并使接触复苏水团时恢复的水中耐力与生命值提升25%。"
      },
      "text": "天赋技能|0\n|技能名=点位记忆法\n|描述=在小地图上显示周围复苏水团的位置，并使接触复苏水团时恢复的水中耐力与生命值提升25%。"
    },
    {
      "type": "template",
      "name": "角色/技能升级材料简",
      "args": [],
      "data": {
        "技能BOSS材料": "亘古树海之一瞬",
        "技能天赋材料序列": "秩序",
        "技能普通材料序列": "齿轮"
      },
      "text": "角色/技能升级材料简\n|技能BOSS材料=亘古树海之一瞬\n|技能天赋材料序列=秩序\n|技能普通材料序列=齿轮"
    },
    {
      "type": "heading",
      "level": 2,
      "text": "角色搭配推荐"
    },
    {
      "type": "template",
      "name": "角色搭配推荐全新改版提示",
      "args": [],
      "data": {},
      "text": "角色搭配推荐全新改版提示"
    },
    {
      "type": "heading",
      "level": 2,
      "text": "角色相关"
    },
    {
      "type": "heading",
      "level": 3,
      "text": "官方介绍"
    },
    {
      "type": "heading",
      "level": 4,
      "text": "壹·人物"
    },
    {
      "type": "text",
      "text": "水中窥月，洞见夜明\n\n=========="
    },
    {
      "type": "template",
      "name": "切换板",
      "args": [
        "开始"
      ],
      "data": {},
      "text": "切换板|开始"
    },
    {
      "type": "template",
      "name": "切换板",
      "args": [
        "默认显示",
        "角色介绍1"
      ],
      "data": {},
      "text": "切换板|默认显示|角色介绍1"
    },
    {
      "type": "template",
      "name": "切换板",
      "args": [
        "默认折叠",
        "角色介绍2"
      ],
      "data": {},
      "text": "切换板|默认折叠|角色介绍2"
    },
    {
      "type": "template",
      "name": "切换板",
      "args": [
        "显示内容"
      ],
      "data": {},
      "text": "切换板|显示内容"
    },
    {
      "type": "text",
      "text": "thumb|200px|琳妮特官方介绍图\n「已经是这个月第五次了…唉，你还没记住不要惹"
    },
    {
      "type": "template",
      "name": "图标",
      "args": [
        "琳妮特"
      ],
      "data": {},
      "text": "图标|琳妮特"
    },
    {
      "type": "text",
      "text": "吗？」\n\n——深夜"
    },
    {
      "type": "template",
      "name": "图标",
      "args": [
        "林尼"
      ],
      "data": {},
      "text": "图标|林尼"
    },
    {
      "type": "text",
      "text": "走出房间时，听见"
    },
    {
      "type": "template",
      "name": "图标",
      "args": [
        "菲米尼"
      ],
      "data": {},
      "text": "图标|菲米尼"
    },
    {
      "type": "text",
      "text": "独自对吸尘器低语。\n\n与那位自称「全提瓦特最棒的大魔术师」的兄长不同，琳妮特恐怕是全提瓦特最低调的魔术助手。\n\n她从不追求鲜花与喝彩，甚至有意避开采访与关注。\n\n外界对她或是好奇，或是招揽，都被她用「已进入待机模式」、「今日需要发呆」之类费解的话拒之门外。\n\n即使有地位颇高的观众登门造访，琳妮特也总是往后一躲，让林尼出面接待。而她则会泡好一壶红茶，坐在一旁默默垂眸啜饮，似乎对会话漠不关心。\n\n只有极少数的客人，能在与林尼畅谈的隙间，察觉到一丝转瞬即逝的锐利视线。但想要追寻视线来源时，却又茫然无踪。\n\n在场者只有盛情依旧的林尼，与自始至终都在专心品茶的琳妮特而已。\n\n…或许只是错觉吧。\n\n…即使不是错觉，只不过是被谁多看了一眼，又能看出些什么呢？"
    },
    {
      "type": "template",
      "name": "切换板",
      "args": [
        "内容结束"
      ],
      "data": {},
      "text": "切换板|内容结束"
    },
    {
      "type": "template",
      "name": "切换板",
      "args": [
        "折叠内容"
      ],
      "data": {},
      "text": "切换板|折叠内容"
    },
    {
      "type": "text",
      "text": "thumb|200px|琳妮特官方介绍图"
    },
    {
      "type": "template",
      "name": "颜色",
      "args": [
        "蓝",
        "「无须困扰，亦无须改变你的习惯。需知，真正的理解可遇不可求，能读懂『信号』的才是同伴。」\n\n——阿蕾奇诺"
      ],
      "data": {},
      "text": "颜色|蓝|「无须困扰，亦无须改变你的习惯。需知，真正的理解可遇不可求，能读懂『信号』的才是同伴。」\n\n——阿蕾奇诺"
    },
    {
      "type": "text",
      "text": "在「布法蒂公馆」的三人小队中，琳妮特是保证团队灵活运转的粘合剂。当意气风发的林尼和谨言慎行的菲米尼在行动策略上发生冲突之时，琳妮特并不站向任何一边，而是冷静提出自己收集到的情报，分析现状，中和两人的意见，最终达成一致结论。\n\n平日里沉默寡言的她，视线总是在「家人」的身上停留。当林尼在演出时意外擦破了手指，或是菲米尼的眼神蒙上了一层忧郁，琳妮特默默将这些信息记下，随后挑选合适的时机，给林尼递上绷带，为菲米尼送去泡好的热茶。\n\n爱着「家人」的她，也被「家人」所爱。从温暖的壁炉旁边醒来，看到林尼在餐桌旁练习卡牌魔术，菲米尼在客厅清理地毯，她恍然察觉，那些因警惕危险而夜不成寐的日子，就像炉火中烧尽的炭一样，已经很久未曾被她记起了。"
    },
    {
      "type": "template",
      "name": "切换板",
      "args": [
        "内容结束"
      ],
      "data": {},
      "text": "切换板|内容结束"
    },
    {
      "type": "template",
      "name": "切换板",
      "args": [
        "结束"
      ],
      "data": {},
      "text": "切换板|结束"
    },
    {
      "type": "heading",
      "level": 4,
      "text": "贰·故事"
    },
    {
      "type": "text",
      "text": "thumb|240px|琳妮特官方故事图\n\n提起枫丹廷最有名气的魔术师，观众一定会想起舞台上神采飞扬的林尼。\n\n但提起枫丹廷最有名气的魔术助手，观众们就往往摸头不着，莫衷一是了。\n\n----\n\n喝彩并非为她而起，掌声亦非为她而鸣。身为助手，她只会在必要的时机引开观众注意，再将高光时刻还予主角。\n\n无论是在台上还是台下，琳妮特总是习惯性地将自己藏在林尼身后，那一小块灯光与赞誉都照不进的影子里。\n\n----\n\n对于一名魔术助手而言，保持低调是一种职业素养。\n\n对于「家」里的孩子而言…\n\n隐匿于影，更是一种生存之道。"
    },
    {
      "type": "heading",
      "level": 3,
      "text": "剧情相关"
    },
    {
      "type": "text",
      "text": "第四章·第一幕「白露与黑潮的序诗」\n\n第四章·第三幕「向深水中的晨星」\n\n第四章·第四幕「谕示胎动的终焉之刻」\n\n第四章·第五幕「罪人舞步旋」\n\n黑斑猫之章·第一幕「被遗忘的怪盗」\n\n丝切铗之章·第一幕「当他们谈起今夜」\n\n邀约事件·琳妮特·第一幕「猫与随机数」\n\n净炼火之章·第一幕「炉火熄灭之际」"
    },
    {
      "type": "heading",
      "level": 3,
      "text": "活动相关"
    },
    {
      "type": "template",
      "name": "人物出场",
      "args": [
        "PAGENAME",
        "活动"
      ],
      "data": {},
      "text": "人物出场|PAGENAME|活动"
    },
    {
      "type": "heading",
      "level": 3,
      "text": "官方贺图"
    },
    {
      "type": "text",
      "text": "生日贺图"
    },
    {
      "type": "template",
      "name": "角色生日贺图板",
      "args": [
        "2024",
        "2026"
      ],
      "data": {},
      "text": "角色生日贺图板|2024|2026"
    },
    {
      "type": "text",
      "text": "节日贺图"
    },
    {
      "type": "template",
      "name": "切换板",
      "args": [
        "开始"
      ],
      "data": {},
      "text": "切换板|开始"
    },
    {
      "type": "template",
      "name": "切换板",
      "args": [
        "默认显示",
        "2024情人节"
      ],
      "data": {},
      "text": "切换板|默认显示|2024情人节"
    },
    {
      "type": "template",
      "name": "切换板",
      "args": [
        "显示内容"
      ],
      "data": {},
      "text": "切换板|显示内容"
    },
    {
      "type": "template",
      "name": "#section-h:角色贺图/节日贺图",
      "args": [
        "2024情人节·琳妮特"
      ],
      "data": {},
      "text": "#section-h:角色贺图/节日贺图|2024情人节·琳妮特"
    },
    {
      "type": "template",
      "name": "切换板",
      "args": [
        "内容结束"
      ],
      "data": {},
      "text": "切换板|内容结束"
    },
    {
      "type": "template",
      "name": "切换板",
      "args": [
        "结束"
      ],
      "data": {},
      "text": "切换板|结束"
    },
    {
      "type": "heading",
      "level": 3,
      "text": "角色宣传视频"
    },
    {
      "type": "text",
      "text": "[https://www.bilibili.com/video/BV18u4y197uv/ 《原神》角色演示-「琳妮特：箱中窥猫」]\n\n[https://www.bilibili.com/video/BV1Qp4y1g7hD/ 《原神》拾枝杂谈-「琳妮特：影中破伪」]"
    },
    {
      "type": "heading",
      "level": 3,
      "text": "人物考据"
    },
    {
      "type": "text",
      "text": "body{background:url('https://patchwiki.biligame.com/images/ys/1/1b/e5yt56nevwbjacq2cixysxhhtv4dvr9.png')  no-repeat fixed 50% 0;background-size: cover;}#mw-content-text{background:#F8F3EF99;}"
    },
    {
      "type": "template",
      "name": "原神WIKI导航",
      "args": [],
      "data": {},
      "text": "原神WIKI导航"
    }
  ]
}